extracurrencyexchange/__init__.py
extracurrencyexchange/core.py
extracurrencyexchange-0.1.0.dist-info/licenses/LICENSE
extracurrencyexchange-0.1.0.dist-info/METADATA
extracurrencyexchange-0.1.0.dist-info/WHEEL
extracurrencyexchange-0.1.0.dist-info/entry_points.txt
extracurrencyexchange-0.1.0.dist-info/top_level.txt
extracurrencyexchange-0.1.0.dist-info/RECORD
